Metadata-Version: 2.1
Name: CustomTkinterMessagebox
Version: 0.0.2
Summary: Messagebox for CustomTkinter
Author: Jorge Magno
Author-email: jorge.estudos0@gmail.com
License: MIT License
Keywords: customtkinter
License-File: LICENSE
Requires-Dist: pillow
Requires-Dist: customtkinter
